cycompi/README.MD
cycompi/__init__.py
cycompi/requirements.txt
cycompi/thirdparty.json
cycompi-0.13.dist-info/LICENSE.rst
cycompi-0.13.dist-info/METADATA
cycompi-0.13.dist-info/WHEEL
cycompi-0.13.dist-info/top_level.txt
cycompi-0.13.dist-info/RECORD
