Metadata-Version: 2.1
Name: cycompi
Version: 0.13
Summary: Cython Compilation Made Simple
Home-page: https://github.com/hansalemaos/cycompi
Author: Johannes Fischer
Author-email: aulasparticularesdealemaosp@gmail.com
License: MIT
Keywords: numpy,C,cython
Classifier: Development Status :: 4 - Beta
Classifier: Programming Language :: Python :: 3 :: Only
Classifier: Programming Language :: Python :: 3.10
Classifier: Topic :: Software Development :: Libraries :: Python Modules
Classifier: Topic :: Utilities
License-File: LICENSE.rst
Requires-Dist: Cython
Requires-Dist: setuptools
